formaldict/__init__.py
formaldict/core.py
formaldict/exceptions.py
formaldict/version.py
formaldict-1.1.0.dist-info/LICENSE
formaldict-1.1.0.dist-info/METADATA
formaldict-1.1.0.dist-info/WHEEL
formaldict-1.1.0.dist-info/RECORD
