Metadata-Version: 2.1
Name: formaldict
Version: 1.1.0
Summary: Formal structured dictionaries parsed from a schema
Home-page: https://github.com/Opus10/formaldict
License: BSD-3-Clause
Author: Wes Kendall
Requires-Python: >=3.9.0,<4
Classifier: Intended Audience :: Developers
Classifier: License :: OSI Approved :: BSD License
Classifier: Operating System :: OS Independent
Classifier: Programming Language :: Python
Classifier: Programming Language :: Python :: 3
Classifier: Programming Language :: Python :: 3.9
Classifier: Programming Language :: Python :: 3.10
Classifier: Programming Language :: Python :: 3.11
Classifier: Programming Language :: Python :: 3.12
Classifier: Programming Language :: Python :: 3.13
Classifier: Programming Language :: Python :: 3 :: Only
Requires-Dist: kmatch (>=0.3.0)
Requires-Dist: prompt-toolkit (>=3.0.2)
Requires-Dist: python-dateutil (>=2.8.1)
Project-URL: Documentation, https://formaldict.readthedocs.io
Project-URL: Repository, https://github.com/Opus10/formaldict
